birdwell/mapping/__init__.py
birdwell/mapping/cache.py
birdwell/mapping/configure.py
birdwell/mapping/pickles.py
birdwell/mapping/redis_.py
birdwell/mapping/toml.py
birdwell_mapping-0.1.1rc13.dev1.dist-info/LICENSE
birdwell_mapping-0.1.1rc13.dev1.dist-info/METADATA
birdwell_mapping-0.1.1rc13.dev1.dist-info/WHEEL
birdwell_mapping-0.1.1rc13.dev1.dist-info/top_level.txt
birdwell_mapping-0.1.1rc13.dev1.dist-info/RECORD
