Metadata-Version: 2.1
Name: birdwell-mapping
Version: 0.1.1rc13.dev1
Summary: file-object mapping submodule of the birdwell namespace package
Author-email: jcbirdwell <jcbirdwell@gmail.com>
License: MIT License
Classifier: Development Status :: 3 - Alpha
Requires-Python: >=3.12
License-File: LICENSE
Requires-Dist: redis
Requires-Dist: tomlkit
